Metadata-Version: 2.1
Name: sveder
Version: 0.11
Summary: Visit sveder.com :)
Home-page: https://github.com/Sveder/import-sveder
Author: Sveder
Author-email: m@sveder.com
License: UNKNOWN
Download-URL: https://github.com/Sveder/import-sveder/archive/0.1.tar.gz
Keywords: sveder,shameless,self,promotion
Platform: UNKNOWN
License-File: LICENSE
